ovos_PHAL_plugin_alsa/__init__.py
ovos_PHAL_plugin_alsa/version.py
ovos_phal_plugin_alsa-0.1.6.dist-info/licenses/LICENSE
ovos_phal_plugin_alsa-0.1.6.dist-info/METADATA
ovos_phal_plugin_alsa-0.1.6.dist-info/WHEEL
ovos_phal_plugin_alsa-0.1.6.dist-info/entry_points.txt
ovos_phal_plugin_alsa-0.1.6.dist-info/top_level.txt
ovos_phal_plugin_alsa-0.1.6.dist-info/zip-safe
ovos_phal_plugin_alsa-0.1.6.dist-info/RECORD
