Metadata-Version: 2.4
Name: ovos_PHAL_plugin_alsa
Version: 0.1.6
Summary: A volume control plugin for OpenVoiceOS hardware abstraction layer
Home-page: https://github.com/OpenVoiceOS/ovos-PHAL-plugin-alsa
Author: JarbasAi
Author-email: jarbasai@mailfence.com
License: Apache-2.0
Classifier: Development Status :: 3 - Alpha
Classifier: Intended Audience :: Developers
Classifier: Topic :: Text Processing :: Linguistic
Classifier: License :: OSI Approved :: Apache Software License
Classifier: Programming Language :: Python :: 3.5
Classifier: Programming Language :: Python :: 3.6
License-File: LICENSE
Requires-Dist: ovos-plugin-manager<3.0.0,>=0.0.1
Requires-Dist: ovos-bus-client<2.0.0,>=0.0.4
Requires-Dist: json_database~=0.7
Requires-Dist: pyalsaaudio~=0.9
Dynamic: author
Dynamic: author-email
Dynamic: classifier
Dynamic: description
Dynamic: description-content-type
Dynamic: home-page
Dynamic: license
Dynamic: license-file
Dynamic: requires-dist
Dynamic: summary
